{
  "4401": {
    "Id": 4401,
    "GroupId": 44,
    "Title": "PenguinCard.4401.1",
    "Desc": "PenguinCard.4401.2",
    "Rarity": 1,
    "Level": 1,
    "MaxLevel": 3,
    "SoldPrice": 10,
    "TriggerPhase": 3,
    "TriggerType": 1,
    "TriggerProbability": 100,
    "TriggerLimit": 1,
    "GrowthType": 1,
    "EffectType": 3,
    "EffectParam": "[100]",
    "Icon": "PengBuildCard_400"
  },
  "4402": {
    "Id": 4402,
    "GroupId": 44,
    "Title": "PenguinCard.4402.1",
    "Desc": "PenguinCard.4402.2",
    "Rarity": 1,
    "Level": 2,
    "MaxLevel": 3,
    "SoldPrice": 10,
    "TriggerPhase": 3,
    "TriggerType": 1,
    "TriggerProbability": 100,
    "TriggerLimit": 1,
    "GrowthType": 1,
    "EffectType": 3,
    "EffectParam": "[200]",
    "Icon": "PengBuildCard_400"
  },
  "4403": {
    "Id": 4403,
    "GroupId": 44,
    "Title": "PenguinCard.4403.1",
    "Desc": "PenguinCard.4403.2",
    "Rarity": 1,
    "Level": 3,
    "MaxLevel": 3,
    "SoldPrice": 10,
    "TriggerPhase": 3,
    "TriggerType": 1,
    "TriggerProbability": 100,
    "TriggerLimit": 1,
    "GrowthType": 1,
    "EffectType": 3,
    "EffectParam": "[300]",
    "Icon": "PengBuildCard_400"
  },
  "5401": {
    "Id": 5401,
    "GroupId": 54,
    "Title": "PenguinCard.5401.1",
    "Desc": "PenguinCard.5401.2",
    "Rarity": 1,
    "Level": 1,
    "MaxLevel": 3,
    "SoldPrice": 10,
    "TriggerPhase": 3,
    "TriggerType": 1,
    "TriggerProbability": 100,
    "TriggerLimit": 1,
    "GrowthType": 1,
    "EffectType": 4,
    "EffectParam": "[0.3]",
    "Icon": "PengBuildCard_500"
  },
  "5402": {
    "Id": 5402,
    "GroupId": 54,
    "Title": "PenguinCard.5402.1",
    "Desc": "PenguinCard.5402.2",
    "Rarity": 1,
    "Level": 2,
    "MaxLevel": 3,
    "SoldPrice": 10,
    "TriggerPhase": 3,
    "TriggerType": 1,
    "TriggerProbability": 100,
    "TriggerLimit": 1,
    "GrowthType": 1,
    "EffectType": 4,
    "EffectParam": "[0.6]",
    "Icon": "PengBuildCard_500"
  },
  "5403": {
    "Id": 5403,
    "GroupId": 54,
    "Title": "PenguinCard.5403.1",
    "Desc": "PenguinCard.5403.2",
    "Rarity": 1,
    "Level": 3,
    "MaxLevel": 3,
    "SoldPrice": 10,
    "TriggerPhase": 3,
    "TriggerType": 1,
    "TriggerProbability": 100,
    "TriggerLimit": 1,
    "GrowthType": 1,
    "EffectType": 4,
    "EffectParam": "[1]",
    "Icon": "PengBuildCard_500"
  },
  "7101": {
    "Id": 7101,
    "GroupId": 71,
    "Title": "PenguinCard.7101.1",
    "Desc": "PenguinCard.7101.2",
    "Rarity": 1,
    "Level": 1,
    "MaxLevel": 5,
    "SoldPrice": 10,
    "TriggerPhase": 2,
    "TriggerType": 2,
    "TriggerParam": "[1]",
    "TriggerProbability": 100,
    "TriggerLimit": 1,
    "GrowthType": 1,
    "EffectType": 3,
    "EffectParam": "[100]",
    "Icon": "PengBuildCard_110"
  },
  "7102": {
    "Id": 7102,
    "GroupId": 71,
    "Title": "PenguinCard.7102.1",
    "Desc": "PenguinCard.7102.2",
    "Rarity": 1,
    "Level": 2,
    "MaxLevel": 5,
    "SoldPrice": 10,
    "TriggerPhase": 2,
    "TriggerType": 2,
    "TriggerParam": "[1]",
    "TriggerProbability": 100,
    "TriggerLimit": 1,
    "GrowthType": 1,
    "EffectType": 3,
    "EffectParam": "[200]",
    "Icon": "PengBuildCard_110"
  },
  "7103": {
    "Id": 7103,
    "GroupId": 71,
    "Title": "PenguinCard.7103.1",
    "Desc": "PenguinCard.7103.2",
    "Rarity": 1,
    "Level": 3,
    "MaxLevel": 5,
    "SoldPrice": 10,
    "TriggerPhase": 2,
    "TriggerType": 2,
    "TriggerParam": "[1]",
    "TriggerProbability": 100,
    "TriggerLimit": 1,
    "GrowthType": 1,
    "EffectType": 3,
    "EffectParam": "[300]",
    "Icon": "PengBuildCard_110"
  },
  "7104": {
    "Id": 7104,
    "GroupId": 71,
    "Title": "PenguinCard.7104.1",
    "Desc": "PenguinCard.7104.2",
    "Rarity": 1,
    "Level": 4,
    "MaxLevel": 5,
    "SoldPrice": 10,
    "TriggerPhase": 2,
    "TriggerType": 2,
    "TriggerParam": "[1]",
    "TriggerProbability": 100,
    "TriggerLimit": 1,
    "GrowthType": 1,
    "EffectType": 3,
    "EffectParam": "[400]",
    "Icon": "PengBuildCard_110"
  },
  "7105": {
    "Id": 7105,
    "GroupId": 71,
    "Title": "PenguinCard.7105.1",
    "Desc": "PenguinCard.7105.2",
    "Rarity": 1,
    "Level": 5,
    "MaxLevel": 5,
    "SoldPrice": 10,
    "TriggerPhase": 2,
    "TriggerType": 2,
    "TriggerParam": "[1]",
    "TriggerProbability": 100,
    "TriggerLimit": 1,
    "GrowthType": 1,
    "EffectType": 3,
    "EffectParam": "[600]",
    "Icon": "PengBuildCard_110"
  },
  "7201": {
    "Id": 7201,
    "GroupId": 72,
    "Title": "PenguinCard.7201.1",
    "Desc": "PenguinCard.7201.2",
    "Rarity": 1,
    "Level": 1,
    "MaxLevel": 5,
    "SoldPrice": 10,
    "TriggerPhase": 2,
    "TriggerType": 2,
    "TriggerParam": "[2]",
    "TriggerProbability": 100,
    "TriggerLimit": 1,
    "GrowthType": 1,
    "EffectType": 3,
    "EffectParam": "[100]",
    "Icon": "PengBuildCard_120"
  },
  "7202": {
    "Id": 7202,
    "GroupId": 72,
    "Title": "PenguinCard.7202.1",
    "Desc": "PenguinCard.7202.2",
    "Rarity": 1,
    "Level": 2,
    "MaxLevel": 5,
    "SoldPrice": 10,
    "TriggerPhase": 2,
    "TriggerType": 2,
    "TriggerParam": "[2]",
    "TriggerProbability": 100,
    "TriggerLimit": 1,
    "GrowthType": 1,
    "EffectType": 3,
    "EffectParam": "[200]",
    "Icon": "PengBuildCard_120"
  },
  "7203": {
    "Id": 7203,
    "GroupId": 72,
    "Title": "PenguinCard.7203.1",
    "Desc": "PenguinCard.7203.2",
    "Rarity": 1,
    "Level": 3,
    "MaxLevel": 5,
    "SoldPrice": 10,
    "TriggerPhase": 2,
    "TriggerType": 2,
    "TriggerParam": "[2]",
    "TriggerProbability": 100,
    "TriggerLimit": 1,
    "GrowthType": 1,
    "EffectType": 3,
    "EffectParam": "[300]",
    "Icon": "PengBuildCard_120"
  },
  "7204": {
    "Id": 7204,
    "GroupId": 72,
    "Title": "PenguinCard.7204.1",
    "Desc": "PenguinCard.7204.2",
    "Rarity": 1,
    "Level": 4,
    "MaxLevel": 5,
    "SoldPrice": 10,
    "TriggerPhase": 2,
    "TriggerType": 2,
    "TriggerParam": "[2]",
    "TriggerProbability": 100,
    "TriggerLimit": 1,
    "GrowthType": 1,
    "EffectType": 3,
    "EffectParam": "[400]",
    "Icon": "PengBuildCard_120"
  },
  "7205": {
    "Id": 7205,
    "GroupId": 72,
    "Title": "PenguinCard.7205.1",
    "Desc": "PenguinCard.7205.2",
    "Rarity": 1,
    "Level": 5,
    "MaxLevel": 5,
    "SoldPrice": 10,
    "TriggerPhase": 2,
    "TriggerType": 2,
    "TriggerParam": "[2]",
    "TriggerProbability": 100,
    "TriggerLimit": 1,
    "GrowthType": 1,
    "EffectType": 3,
    "EffectParam": "[600]",
    "Icon": "PengBuildCard_120"
  },
  "7301": {
    "Id": 7301,
    "GroupId": 73,
    "Title": "PenguinCard.7301.1",
    "Desc": "PenguinCard.7301.2",
    "Rarity": 1,
    "Level": 1,
    "MaxLevel": 5,
    "SoldPrice": 10,
    "TriggerPhase": 2,
    "TriggerType": 2,
    "TriggerParam": "[3]",
    "TriggerProbability": 100,
    "TriggerLimit": 1,
    "GrowthType": 1,
    "EffectType": 3,
    "EffectParam": "[100]",
    "Icon": "PengBuildCard_130"
  },
  "7302": {
    "Id": 7302,
    "GroupId": 73,
    "Title": "PenguinCard.7302.1",
    "Desc": "PenguinCard.7302.2",
    "Rarity": 1,
    "Level": 2,
    "MaxLevel": 5,
    "SoldPrice": 10,
    "TriggerPhase": 2,
    "TriggerType": 2,
    "TriggerParam": "[3]",
    "TriggerProbability": 100,
    "TriggerLimit": 1,
    "GrowthType": 1,
    "EffectType": 3,
    "EffectParam": "[200]",
    "Icon": "PengBuildCard_130"
  },
  "7303": {
    "Id": 7303,
    "GroupId": 73,
    "Title": "PenguinCard.7303.1",
    "Desc": "PenguinCard.7303.2",
    "Rarity": 1,
    "Level": 3,
    "MaxLevel": 5,
    "SoldPrice": 10,
    "TriggerPhase": 2,
    "TriggerType": 2,
    "TriggerParam": "[3]",
    "TriggerProbability": 100,
    "TriggerLimit": 1,
    "GrowthType": 1,
    "EffectType": 3,
    "EffectParam": "[300]",
    "Icon": "PengBuildCard_130"
  },
  "7304": {
    "Id": 7304,
    "GroupId": 73,
    "Title": "PenguinCard.7304.1",
    "Desc": "PenguinCard.7304.2",
    "Rarity": 1,
    "Level": 4,
    "MaxLevel": 5,
    "SoldPrice": 10,
    "TriggerPhase": 2,
    "TriggerType": 2,
    "TriggerParam": "[3]",
    "TriggerProbability": 100,
    "TriggerLimit": 1,
    "GrowthType": 1,
    "EffectType": 3,
    "EffectParam": "[400]",
    "Icon": "PengBuildCard_130"
  },
  "7305": {
    "Id": 7305,
    "GroupId": 73,
    "Title": "PenguinCard.7305.1",
    "Desc": "PenguinCard.7305.2",
    "Rarity": 1,
    "Level": 5,
    "MaxLevel": 5,
    "SoldPrice": 10,
    "TriggerPhase": 2,
    "TriggerType": 2,
    "TriggerParam": "[3]",
    "TriggerProbability": 100,
    "TriggerLimit": 1,
    "GrowthType": 1,
    "EffectType": 3,
    "EffectParam": "[600]",
    "Icon": "PengBuildCard_130"
  },
  "3101": {
    "Id": 3101,
    "GroupId": 31,
    "Title": "PenguinCard.3101.1",
    "Desc": "PenguinCard.3101.2",
    "Rarity": 1,
    "Level": 1,
    "MaxLevel": 5,
    "SoldPrice": 10,
    "TriggerPhase": 2,
    "TriggerType": 2,
    "TriggerParam": "[1]",
    "TriggerProbability": 100,
    "TriggerLimit": 1,
    "GrowthType": 1,
    "EffectType": 4,
    "EffectParam": "[0.3]",
    "Icon": "PengBuildCard_610"
  },
  "3102": {
    "Id": 3102,
    "GroupId": 31,
    "Title": "PenguinCard.3102.1",
    "Desc": "PenguinCard.3102.2",
    "Rarity": 1,
    "Level": 2,
    "MaxLevel": 5,
    "SoldPrice": 10,
    "TriggerPhase": 2,
    "TriggerType": 2,
    "TriggerParam": "[1]",
    "TriggerProbability": 100,
    "TriggerLimit": 1,
    "GrowthType": 1,
    "EffectType": 4,
    "EffectParam": "[0.4]",
    "Icon": "PengBuildCard_610"
  },
  "3103": {
    "Id": 3103,
    "GroupId": 31,
    "Title": "PenguinCard.3103.1",
    "Desc": "PenguinCard.3103.2",
    "Rarity": 1,
    "Level": 3,
    "MaxLevel": 5,
    "SoldPrice": 10,
    "TriggerPhase": 2,
    "TriggerType": 2,
    "TriggerParam": "[1]",
    "TriggerProbability": 100,
    "TriggerLimit": 1,
    "GrowthType": 1,
    "EffectType": 4,
    "EffectParam": "[0.6]",
    "Icon": "PengBuildCard_610"
  },
  "3104": {
    "Id": 3104,
    "GroupId": 31,
    "Title": "PenguinCard.3104.1",
    "Desc": "PenguinCard.3104.2",
    "Rarity": 1,
    "Level": 4,
    "MaxLevel": 5,
    "SoldPrice": 10,
    "TriggerPhase": 2,
    "TriggerType": 2,
    "TriggerParam": "[1]",
    "TriggerProbability": 100,
    "TriggerLimit": 1,
    "GrowthType": 1,
    "EffectType": 4,
    "EffectParam": "[0.8]",
    "Icon": "PengBuildCard_610"
  },
  "3105": {
    "Id": 3105,
    "GroupId": 31,
    "Title": "PenguinCard.3105.1",
    "Desc": "PenguinCard.3105.2",
    "Rarity": 1,
    "Level": 5,
    "MaxLevel": 5,
    "SoldPrice": 10,
    "TriggerPhase": 2,
    "TriggerType": 2,
    "TriggerParam": "[1]",
    "TriggerProbability": 100,
    "TriggerLimit": 1,
    "GrowthType": 1,
    "EffectType": 4,
    "EffectParam": "[1.2]",
    "Icon": "PengBuildCard_610"
  },
  "3201": {
    "Id": 3201,
    "GroupId": 32,
    "Title": "PenguinCard.3201.1",
    "Desc": "PenguinCard.3201.2",
    "Rarity": 1,
    "Level": 1,
    "MaxLevel": 5,
    "SoldPrice": 10,
    "TriggerPhase": 2,
    "TriggerType": 2,
    "TriggerParam": "[2]",
    "TriggerProbability": 100,
    "TriggerLimit": 1,
    "GrowthType": 1,
    "EffectType": 4,
    "EffectParam": "[0.3]",
    "Icon": "PengBuildCard_620"
  },
  "3202": {
    "Id": 3202,
    "GroupId": 32,
    "Title": "PenguinCard.3202.1",
    "Desc": "PenguinCard.3202.2",
    "Rarity": 1,
    "Level": 2,
    "MaxLevel": 5,
    "SoldPrice": 10,
    "TriggerPhase": 2,
    "TriggerType": 2,
    "TriggerParam": "[2]",
    "TriggerProbability": 100,
    "TriggerLimit": 1,
    "GrowthType": 1,
    "EffectType": 4,
    "EffectParam": "[0.4]",
    "Icon": "PengBuildCard_620"
  },
  "3203": {
    "Id": 3203,
    "GroupId": 32,
    "Title": "PenguinCard.3203.1",
    "Desc": "PenguinCard.3203.2",
    "Rarity": 1,
    "Level": 3,
    "MaxLevel": 5,
    "SoldPrice": 10,
    "TriggerPhase": 2,
    "TriggerType": 2,
    "TriggerParam": "[2]",
    "TriggerProbability": 100,
    "TriggerLimit": 1,
    "GrowthType": 1,
    "EffectType": 4,
    "EffectParam": "[0.6]",
    "Icon": "PengBuildCard_620"
  },
  "3204": {
    "Id": 3204,
    "GroupId": 32,
    "Title": "PenguinCard.3204.1",
    "Desc": "PenguinCard.3204.2",
    "Rarity": 1,
    "Level": 4,
    "MaxLevel": 5,
    "SoldPrice": 10,
    "TriggerPhase": 2,
    "TriggerType": 2,
    "TriggerParam": "[2]",
    "TriggerProbability": 100,
    "TriggerLimit": 1,
    "GrowthType": 1,
    "EffectType": 4,
    "EffectParam": "[0.8]",
    "Icon": "PengBuildCard_620"
  },
  "3205": {
    "Id": 3205,
    "GroupId": 32,
    "Title": "PenguinCard.3205.1",
    "Desc": "PenguinCard.3205.2",
    "Rarity": 1,
    "Level": 5,
    "MaxLevel": 5,
    "SoldPrice": 10,
    "TriggerPhase": 2,
    "TriggerType": 2,
    "TriggerParam": "[2]",
    "TriggerProbability": 100,
    "TriggerLimit": 1,
    "GrowthType": 1,
    "EffectType": 4,
    "EffectParam": "[1.2]",
    "Icon": "PengBuildCard_620"
  },
  "3301": {
    "Id": 3301,
    "GroupId": 33,
    "Title": "PenguinCard.3301.1",
    "Desc": "PenguinCard.3301.2",
    "Rarity": 1,
    "Level": 1,
    "MaxLevel": 5,
    "SoldPrice": 10,
    "TriggerPhase": 2,
    "TriggerType": 2,
    "TriggerParam": "[3]",
    "TriggerProbability": 100,
    "TriggerLimit": 1,
    "GrowthType": 1,
    "EffectType": 4,
    "EffectParam": "[0.3]",
    "Icon": "PengBuildCard_630"
  },
  "3302": {
    "Id": 3302,
    "GroupId": 33,
    "Title": "PenguinCard.3302.1",
    "Desc": "PenguinCard.3302.2",
    "Rarity": 1,
    "Level": 2,
    "MaxLevel": 5,
    "SoldPrice": 10,
    "TriggerPhase": 2,
    "TriggerType": 2,
    "TriggerParam": "[3]",
    "TriggerProbability": 100,
    "TriggerLimit": 1,
    "GrowthType": 1,
    "EffectType": 4,
    "EffectParam": "[0.4]",
    "Icon": "PengBuildCard_630"
  },
  "3303": {
    "Id": 3303,
    "GroupId": 33,
    "Title": "PenguinCard.3303.1",
    "Desc": "PenguinCard.3303.2",
    "Rarity": 1,
    "Level": 3,
    "MaxLevel": 5,
    "SoldPrice": 10,
    "TriggerPhase": 2,
    "TriggerType": 2,
    "TriggerParam": "[3]",
    "TriggerProbability": 100,
    "TriggerLimit": 1,
    "GrowthType": 1,
    "EffectType": 4,
    "EffectParam": "[0.6]",
    "Icon": "PengBuildCard_630"
  },
  "3304": {
    "Id": 3304,
    "GroupId": 33,
    "Title": "PenguinCard.3304.1",
    "Desc": "PenguinCard.3304.2",
    "Rarity": 1,
    "Level": 4,
    "MaxLevel": 5,
    "SoldPrice": 10,
    "TriggerPhase": 2,
    "TriggerType": 2,
    "TriggerParam": "[3]",
    "TriggerProbability": 100,
    "TriggerLimit": 1,
    "GrowthType": 1,
    "EffectType": 4,
    "EffectParam": "[0.8]",
    "Icon": "PengBuildCard_630"
  },
  "3305": {
    "Id": 3305,
    "GroupId": 33,
    "Title": "PenguinCard.3305.1",
    "Desc": "PenguinCard.3305.2",
    "Rarity": 1,
    "Level": 5,
    "MaxLevel": 5,
    "SoldPrice": 10,
    "TriggerPhase": 2,
    "TriggerType": 2,
    "TriggerParam": "[3]",
    "TriggerProbability": 100,
    "TriggerLimit": 1,
    "GrowthType": 1,
    "EffectType": 4,
    "EffectParam": "[1.2]",
    "Icon": "PengBuildCard_630"
  },
  "4101": {
    "Id": 4101,
    "GroupId": 41,
    "Title": "PenguinCard.4101.1",
    "Desc": "PenguinCard.4101.2",
    "Rarity": 1,
    "Level": 1,
    "MaxLevel": 5,
    "SoldPrice": 10,
    "TriggerPhase": 3,
    "TriggerType": 3,
    "TriggerParam": "{\"1\":2}",
    "TriggerProbability": 100,
    "TriggerLimit": 1,
    "GrowthType": 1,
    "EffectType": 3,
    "EffectParam": "[300]",
    "Icon": "PengBuildCard_410"
  },
  "4102": {
    "Id": 4102,
    "GroupId": 41,
    "Title": "PenguinCard.4102.1",
    "Desc": "PenguinCard.4102.2",
    "Rarity": 1,
    "Level": 2,
    "MaxLevel": 5,
    "SoldPrice": 10,
    "TriggerPhase": 3,
    "TriggerType": 3,
    "TriggerParam": "{\"1\":2}",
    "TriggerProbability": 100,
    "TriggerLimit": 1,
    "GrowthType": 1,
    "EffectType": 3,
    "EffectParam": "[400]",
    "Icon": "PengBuildCard_410"
  },
  "4103": {
    "Id": 4103,
    "GroupId": 41,
    "Title": "PenguinCard.4103.1",
    "Desc": "PenguinCard.4103.2",
    "Rarity": 1,
    "Level": 3,
    "MaxLevel": 5,
    "SoldPrice": 10,
    "TriggerPhase": 3,
    "TriggerType": 3,
    "TriggerParam": "{\"1\":2}",
    "TriggerProbability": 100,
    "TriggerLimit": 1,
    "GrowthType": 1,
    "EffectType": 3,
    "EffectParam": "[600]",
    "Icon": "PengBuildCard_410"
  },
  "4104": {
    "Id": 4104,
    "GroupId": 41,
    "Title": "PenguinCard.4104.1",
    "Desc": "PenguinCard.4104.2",
    "Rarity": 1,
    "Level": 4,
    "MaxLevel": 5,
    "SoldPrice": 10,
    "TriggerPhase": 3,
    "TriggerType": 3,
    "TriggerParam": "{\"1\":2}",
    "TriggerProbability": 100,
    "TriggerLimit": 1,
    "GrowthType": 1,
    "EffectType": 3,
    "EffectParam": "[800]",
    "Icon": "PengBuildCard_410"
  },
  "4105": {
    "Id": 4105,
    "GroupId": 41,
    "Title": "PenguinCard.4105.1",
    "Desc": "PenguinCard.4105.2",
    "Rarity": 1,
    "Level": 5,
    "MaxLevel": 5,
    "SoldPrice": 10,
    "TriggerPhase": 3,
    "TriggerType": 3,
    "TriggerParam": "{\"1\":2}",
    "TriggerProbability": 100,
    "TriggerLimit": 1,
    "GrowthType": 1,
    "EffectType": 3,
    "EffectParam": "[1200]",
    "Icon": "PengBuildCard_410"
  },
  "4201": {
    "Id": 4201,
    "GroupId": 42,
    "Title": "PenguinCard.4201.1",
    "Desc": "PenguinCard.4201.2",
    "Rarity": 1,
    "Level": 1,
    "MaxLevel": 5,
    "SoldPrice": 10,
    "TriggerPhase": 3,
    "TriggerType": 3,
    "TriggerParam": "{\"2\":2}",
    "TriggerProbability": 100,
    "TriggerLimit": 1,
    "GrowthType": 1,
    "EffectType": 3,
    "EffectParam": "[300]",
    "Icon": "PengBuildCard_420"
  },
  "4202": {
    "Id": 4202,
    "GroupId": 42,
    "Title": "PenguinCard.4202.1",
    "Desc": "PenguinCard.4202.2",
    "Rarity": 1,
    "Level": 2,
    "MaxLevel": 5,
    "SoldPrice": 10,
    "TriggerPhase": 3,
    "TriggerType": 3,
    "TriggerParam": "{\"2\":2}",
    "TriggerProbability": 100,
    "TriggerLimit": 1,
    "GrowthType": 1,
    "EffectType": 3,
    "EffectParam": "[400]",
    "Icon": "PengBuildCard_420"
  },
  "4203": {
    "Id": 4203,
    "GroupId": 42,
    "Title": "PenguinCard.4203.1",
    "Desc": "PenguinCard.4203.2",
    "Rarity": 1,
    "Level": 3,
    "MaxLevel": 5,
    "SoldPrice": 10,
    "TriggerPhase": 3,
    "TriggerType": 3,
    "TriggerParam": "{\"2\":2}",
    "TriggerProbability": 100,
    "TriggerLimit": 1,
    "GrowthType": 1,
    "EffectType": 3,
    "EffectParam": "[600]",
    "Icon": "PengBuildCard_420"
  },
  "4204": {
    "Id": 4204,
    "GroupId": 42,
    "Title": "PenguinCard.4204.1",
    "Desc": "PenguinCard.4204.2",
    "Rarity": 1,
    "Level": 4,
    "MaxLevel": 5,
    "SoldPrice": 10,
    "TriggerPhase": 3,
    "TriggerType": 3,
    "TriggerParam": "{\"2\":2}",
    "TriggerProbability": 100,
    "TriggerLimit": 1,
    "GrowthType": 1,
    "EffectType": 3,
    "EffectParam": "[800]",
    "Icon": "PengBuildCard_420"
  },
  "4205": {
    "Id": 4205,
    "GroupId": 42,
    "Title": "PenguinCard.4205.1",
    "Desc": "PenguinCard.4205.2",
    "Rarity": 1,
    "Level": 5,
    "MaxLevel": 5,
    "SoldPrice": 10,
    "TriggerPhase": 3,
    "TriggerType": 3,
    "TriggerParam": "{\"2\":2}",
    "TriggerProbability": 100,
    "TriggerLimit": 1,
    "GrowthType": 1,
    "EffectType": 3,
    "EffectParam": "[1200]",
    "Icon": "PengBuildCard_420"
  },
  "4301": {
    "Id": 4301,
    "GroupId": 43,
    "Title": "PenguinCard.4301.1",
    "Desc": "PenguinCard.4301.2",
    "Rarity": 1,
    "Level": 1,
    "MaxLevel": 5,
    "SoldPrice": 10,
    "TriggerPhase": 3,
    "TriggerType": 3,
    "TriggerParam": "{\"3\":2}",
    "TriggerProbability": 100,
    "TriggerLimit": 1,
    "GrowthType": 1,
    "EffectType": 3,
    "EffectParam": "[300]",
    "Icon": "PengBuildCard_430"
  },
  "4302": {
    "Id": 4302,
    "GroupId": 43,
    "Title": "PenguinCard.4302.1",
    "Desc": "PenguinCard.4302.2",
    "Rarity": 1,
    "Level": 2,
    "MaxLevel": 5,
    "SoldPrice": 10,
    "TriggerPhase": 3,
    "TriggerType": 3,
    "TriggerParam": "{\"3\":2}",
    "TriggerProbability": 100,
    "TriggerLimit": 1,
    "GrowthType": 1,
    "EffectType": 3,
    "EffectParam": "[400]",
    "Icon": "PengBuildCard_430"
  },
  "4303": {
    "Id": 4303,
    "GroupId": 43,
    "Title": "PenguinCard.4303.1",
    "Desc": "PenguinCard.4303.2",
    "Rarity": 1,
    "Level": 3,
    "MaxLevel": 5,
    "SoldPrice": 10,
    "TriggerPhase": 3,
    "TriggerType": 3,
    "TriggerParam": "{\"3\":2}",
    "TriggerProbability": 100,
    "TriggerLimit": 1,
    "GrowthType": 1,
    "EffectType": 3,
    "EffectParam": "[600]",
    "Icon": "PengBuildCard_430"
  },
  "4304": {
    "Id": 4304,
    "GroupId": 43,
    "Title": "PenguinCard.4304.1",
    "Desc": "PenguinCard.4304.2",
    "Rarity": 1,
    "Level": 4,
    "MaxLevel": 5,
    "SoldPrice": 10,
    "TriggerPhase": 3,
    "TriggerType": 3,
    "TriggerParam": "{\"3\":2}",
    "TriggerProbability": 100,
    "TriggerLimit": 1,
    "GrowthType": 1,
    "EffectType": 3,
    "EffectParam": "[800]",
    "Icon": "PengBuildCard_430"
  },
  "4305": {
    "Id": 4305,
    "GroupId": 43,
    "Title": "PenguinCard.4305.1",
    "Desc": "PenguinCard.4305.2",
    "Rarity": 1,
    "Level": 5,
    "MaxLevel": 5,
    "SoldPrice": 10,
    "TriggerPhase": 3,
    "TriggerType": 3,
    "TriggerParam": "{\"3\":2}",
    "TriggerProbability": 100,
    "TriggerLimit": 1,
    "GrowthType": 1,
    "EffectType": 3,
    "EffectParam": "[1200]",
    "Icon": "PengBuildCard_430"
  },
  "2101": {
    "Id": 2101,
    "GroupId": 21,
    "Title": "PenguinCard.2101.1",
    "Desc": "PenguinCard.2101.2",
    "Rarity": 1,
    "Level": 1,
    "MaxLevel": 3,
    "SoldPrice": 10,
    "TriggerPhase": 1,
    "TriggerType": 1,
    "TriggerProbability": 100,
    "TriggerLimit": 1,
    "GrowthType": 1,
    "EffectType": 2,
    "EffectParam": "{\"101\":100}",
    "Icon": "PengBuildCard_310"
  },
  "2102": {
    "Id": 2102,
    "GroupId": 21,
    "Title": "PenguinCard.2102.1",
    "Desc": "PenguinCard.2102.2",
    "Rarity": 1,
    "Level": 2,
    "MaxLevel": 3,
    "SoldPrice": 10,
    "TriggerPhase": 1,
    "TriggerType": 1,
    "TriggerProbability": 100,
    "TriggerLimit": 1,
    "GrowthType": 1,
    "EffectType": 2,
    "EffectParam": "{\"101\":200}",
    "Icon": "PengBuildCard_310"
  },
  "2103": {
    "Id": 2103,
    "GroupId": 21,
    "Title": "PenguinCard.2103.1",
    "Desc": "PenguinCard.2103.2",
    "Rarity": 1,
    "Level": 3,
    "MaxLevel": 3,
    "SoldPrice": 10,
    "TriggerPhase": 1,
    "TriggerType": 1,
    "TriggerProbability": 100,
    "TriggerLimit": 1,
    "GrowthType": 1,
    "EffectType": 2,
    "EffectParam": "{\"101\":300}",
    "Icon": "PengBuildCard_310"
  },
  "2201": {
    "Id": 2201,
    "GroupId": 22,
    "Title": "PenguinCard.2201.1",
    "Desc": "PenguinCard.2201.2",
    "Rarity": 1,
    "Level": 1,
    "MaxLevel": 3,
    "SoldPrice": 10,
    "TriggerPhase": 1,
    "TriggerType": 1,
    "TriggerProbability": 100,
    "TriggerLimit": 1,
    "GrowthType": 1,
    "EffectType": 2,
    "EffectParam": "{\"102\":100}",
    "Icon": "PengBuildCard_320"
  },
  "2202": {
    "Id": 2202,
    "GroupId": 22,
    "Title": "PenguinCard.2202.1",
    "Desc": "PenguinCard.2202.2",
    "Rarity": 1,
    "Level": 2,
    "MaxLevel": 3,
    "SoldPrice": 10,
    "TriggerPhase": 1,
    "TriggerType": 1,
    "TriggerProbability": 100,
    "TriggerLimit": 1,
    "GrowthType": 1,
    "EffectType": 2,
    "EffectParam": "{\"102\":200}",
    "Icon": "PengBuildCard_320"
  },
  "2203": {
    "Id": 2203,
    "GroupId": 22,
    "Title": "PenguinCard.2203.1",
    "Desc": "PenguinCard.2203.2",
    "Rarity": 1,
    "Level": 3,
    "MaxLevel": 3,
    "SoldPrice": 10,
    "TriggerPhase": 1,
    "TriggerType": 1,
    "TriggerProbability": 100,
    "TriggerLimit": 1,
    "GrowthType": 1,
    "EffectType": 2,
    "EffectParam": "{\"102\":300}",
    "Icon": "PengBuildCard_320"
  },
  "2301": {
    "Id": 2301,
    "GroupId": 23,
    "Title": "PenguinCard.2301.1",
    "Desc": "PenguinCard.2301.2",
    "Rarity": 1,
    "Level": 1,
    "MaxLevel": 3,
    "SoldPrice": 10,
    "TriggerPhase": 1,
    "TriggerType": 1,
    "TriggerProbability": 100,
    "TriggerLimit": 1,
    "GrowthType": 1,
    "EffectType": 2,
    "EffectParam": "{\"103\":100}",
    "Icon": "PengBuildCard_330"
  },
  "2302": {
    "Id": 2302,
    "GroupId": 23,
    "Title": "PenguinCard.2302.1",
    "Desc": "PenguinCard.2302.2",
    "Rarity": 1,
    "Level": 2,
    "MaxLevel": 3,
    "SoldPrice": 10,
    "TriggerPhase": 1,
    "TriggerType": 1,
    "TriggerProbability": 100,
    "TriggerLimit": 1,
    "GrowthType": 1,
    "EffectType": 2,
    "EffectParam": "{\"103\":200}",
    "Icon": "PengBuildCard_330"
  },
  "2303": {
    "Id": 2303,
    "GroupId": 23,
    "Title": "PenguinCard.2303.1",
    "Desc": "PenguinCard.2303.2",
    "Rarity": 1,
    "Level": 3,
    "MaxLevel": 3,
    "SoldPrice": 10,
    "TriggerPhase": 1,
    "TriggerType": 1,
    "TriggerProbability": 100,
    "TriggerLimit": 1,
    "GrowthType": 1,
    "EffectType": 2,
    "EffectParam": "{\"103\":300}",
    "Icon": "PengBuildCard_330"
  },
  "1101": {
    "Id": 1101,
    "GroupId": 11,
    "Title": "PenguinCard.1101.1",
    "Desc": "PenguinCard.1101.2",
    "Rarity": 1,
    "Level": 1,
    "MaxLevel": 3,
    "SoldPrice": 10,
    "TriggerPhase": 2,
    "TriggerType": 5,
    "TriggerParam": "[101]",
    "TriggerProbability": 50,
    "TriggerLimit": 3,
    "TriggerLimitParam": 1,
    "GrowthType": 1,
    "EffectType": 1,
    "EffectParam": "[201]",
    "Icon": "PengBuildCard_710"
  },
  "1102": {
    "Id": 1102,
    "GroupId": 11,
    "Title": "PenguinCard.1102.1",
    "Desc": "PenguinCard.1102.2",
    "Rarity": 1,
    "Level": 2,
    "MaxLevel": 3,
    "SoldPrice": 10,
    "TriggerPhase": 2,
    "TriggerType": 5,
    "TriggerParam": "[101]",
    "TriggerProbability": 50,
    "TriggerLimit": 3,
    "TriggerLimitParam": 2,
    "GrowthType": 1,
    "EffectType": 1,
    "EffectParam": "[201]",
    "Icon": "PengBuildCard_710"
  },
  "1103": {
    "Id": 1103,
    "GroupId": 11,
    "Title": "PenguinCard.1103.1",
    "Desc": "PenguinCard.1103.2",
    "Rarity": 1,
    "Level": 3,
    "MaxLevel": 3,
    "SoldPrice": 10,
    "TriggerPhase": 2,
    "TriggerType": 5,
    "TriggerParam": "[101]",
    "TriggerProbability": 50,
    "TriggerLimit": 3,
    "TriggerLimitParam": 3,
    "GrowthType": 1,
    "EffectType": 1,
    "EffectParam": "[201]",
    "Icon": "PengBuildCard_710"
  },
  "1201": {
    "Id": 1201,
    "GroupId": 12,
    "Title": "PenguinCard.1201.1",
    "Desc": "PenguinCard.1201.2",
    "Rarity": 1,
    "Level": 1,
    "MaxLevel": 3,
    "SoldPrice": 10,
    "TriggerPhase": 2,
    "TriggerType": 5,
    "TriggerParam": "[102]",
    "TriggerProbability": 50,
    "TriggerLimit": 3,
    "TriggerLimitParam": 1,
    "GrowthType": 1,
    "EffectType": 1,
    "EffectParam": "[202]",
    "Icon": "PengBuildCard_720"
  },
  "1202": {
    "Id": 1202,
    "GroupId": 12,
    "Title": "PenguinCard.1202.1",
    "Desc": "PenguinCard.1202.2",
    "Rarity": 1,
    "Level": 2,
    "MaxLevel": 3,
    "SoldPrice": 10,
    "TriggerPhase": 2,
    "TriggerType": 5,
    "TriggerParam": "[102]",
    "TriggerProbability": 50,
    "TriggerLimit": 3,
    "TriggerLimitParam": 2,
    "GrowthType": 1,
    "EffectType": 1,
    "EffectParam": "[202]",
    "Icon": "PengBuildCard_720"
  },
  "1203": {
    "Id": 1203,
    "GroupId": 12,
    "Title": "PenguinCard.1203.1",
    "Desc": "PenguinCard.1203.2",
    "Rarity": 1,
    "Level": 3,
    "MaxLevel": 3,
    "SoldPrice": 10,
    "TriggerPhase": 2,
    "TriggerType": 5,
    "TriggerParam": "[102]",
    "TriggerProbability": 50,
    "TriggerLimit": 3,
    "TriggerLimitParam": 3,
    "GrowthType": 1,
    "EffectType": 1,
    "EffectParam": "[202]",
    "Icon": "PengBuildCard_720"
  },
  "1301": {
    "Id": 1301,
    "GroupId": 13,
    "Title": "PenguinCard.1301.1",
    "Desc": "PenguinCard.1301.2",
    "Rarity": 1,
    "Level": 1,
    "MaxLevel": 3,
    "SoldPrice": 10,
    "TriggerPhase": 2,
    "TriggerType": 5,
    "TriggerParam": "[103]",
    "TriggerProbability": 50,
    "TriggerLimit": 3,
    "TriggerLimitParam": 1,
    "GrowthType": 1,
    "EffectType": 1,
    "EffectParam": "[203]",
    "Icon": "PengBuildCard_730"
  },
  "1302": {
    "Id": 1302,
    "GroupId": 13,
    "Title": "PenguinCard.1302.1",
    "Desc": "PenguinCard.1302.2",
    "Rarity": 1,
    "Level": 2,
    "MaxLevel": 3,
    "SoldPrice": 10,
    "TriggerPhase": 2,
    "TriggerType": 5,
    "TriggerParam": "[103]",
    "TriggerProbability": 50,
    "TriggerLimit": 3,
    "TriggerLimitParam": 2,
    "GrowthType": 1,
    "EffectType": 1,
    "EffectParam": "[203]",
    "Icon": "PengBuildCard_730"
  },
  "1303": {
    "Id": 1303,
    "GroupId": 13,
    "Title": "PenguinCard.1303.1",
    "Desc": "PenguinCard.1303.2",
    "Rarity": 1,
    "Level": 3,
    "MaxLevel": 3,
    "SoldPrice": 10,
    "TriggerPhase": 2,
    "TriggerType": 5,
    "TriggerParam": "[103]",
    "TriggerProbability": 50,
    "TriggerLimit": 3,
    "TriggerLimitParam": 3,
    "GrowthType": 1,
    "EffectType": 1,
    "EffectParam": "[203]",
    "Icon": "PengBuildCard_730"
  },
  "5101": {
    "Id": 5101,
    "GroupId": 51,
    "Title": "PenguinCard.5101.1",
    "Desc": "PenguinCard.5101.2",
    "Rarity": 1,
    "Level": 1,
    "MaxLevel": 3,
    "SoldPrice": 10,
    "TriggerPhase": 3,
    "TriggerType": 3,
    "TriggerParam": "{\"1\":3}",
    "TriggerProbability": 100,
    "TriggerLimit": 1,
    "GrowthType": 1,
    "EffectType": 4,
    "EffectParam": "[1.6]",
    "Icon": "PengBuildCard_210"
  },
  "5102": {
    "Id": 5102,
    "GroupId": 51,
    "Title": "PenguinCard.5102.1",
    "Desc": "PenguinCard.5102.2",
    "Rarity": 1,
    "Level": 2,
    "MaxLevel": 3,
    "SoldPrice": 10,
    "TriggerPhase": 3,
    "TriggerType": 3,
    "TriggerParam": "{\"1\":3}",
    "TriggerProbability": 100,
    "TriggerLimit": 1,
    "GrowthType": 1,
    "EffectType": 4,
    "EffectParam": "[3.2]",
    "Icon": "PengBuildCard_210"
  },
  "5103": {
    "Id": 5103,
    "GroupId": 51,
    "Title": "PenguinCard.5103.1",
    "Desc": "PenguinCard.5103.2",
    "Rarity": 1,
    "Level": 3,
    "MaxLevel": 3,
    "SoldPrice": 10,
    "TriggerPhase": 3,
    "TriggerType": 3,
    "TriggerParam": "{\"1\":3}",
    "TriggerProbability": 100,
    "TriggerLimit": 1,
    "GrowthType": 1,
    "EffectType": 4,
    "EffectParam": "[6.5]",
    "Icon": "PengBuildCard_210"
  },
  "5201": {
    "Id": 5201,
    "GroupId": 52,
    "Title": "PenguinCard.5201.1",
    "Desc": "PenguinCard.5201.2",
    "Rarity": 1,
    "Level": 1,
    "MaxLevel": 3,
    "SoldPrice": 10,
    "TriggerPhase": 3,
    "TriggerType": 3,
    "TriggerParam": "{\"2\":3}",
    "TriggerProbability": 100,
    "TriggerLimit": 1,
    "GrowthType": 1,
    "EffectType": 4,
    "EffectParam": "[1.6]",
    "Icon": "PengBuildCard_220"
  },
  "5202": {
    "Id": 5202,
    "GroupId": 52,
    "Title": "PenguinCard.5202.1",
    "Desc": "PenguinCard.5202.2",
    "Rarity": 1,
    "Level": 2,
    "MaxLevel": 3,
    "SoldPrice": 10,
    "TriggerPhase": 3,
    "TriggerType": 3,
    "TriggerParam": "{\"2\":3}",
    "TriggerProbability": 100,
    "TriggerLimit": 1,
    "GrowthType": 1,
    "EffectType": 4,
    "EffectParam": "[3.2]",
    "Icon": "PengBuildCard_220"
  },
  "5203": {
    "Id": 5203,
    "GroupId": 52,
    "Title": "PenguinCard.5203.1",
    "Desc": "PenguinCard.5203.2",
    "Rarity": 1,
    "Level": 3,
    "MaxLevel": 3,
    "SoldPrice": 10,
    "TriggerPhase": 3,
    "TriggerType": 3,
    "TriggerParam": "{\"2\":3}",
    "TriggerProbability": 100,
    "TriggerLimit": 1,
    "GrowthType": 1,
    "EffectType": 4,
    "EffectParam": "[6.5]",
    "Icon": "PengBuildCard_220"
  },
  "5301": {
    "Id": 5301,
    "GroupId": 53,
    "Title": "PenguinCard.5301.1",
    "Desc": "PenguinCard.5301.2",
    "Rarity": 1,
    "Level": 1,
    "MaxLevel": 3,
    "SoldPrice": 10,
    "TriggerPhase": 3,
    "TriggerType": 3,
    "TriggerParam": "{\"3\":3}",
    "TriggerProbability": 100,
    "TriggerLimit": 1,
    "GrowthType": 1,
    "EffectType": 4,
    "EffectParam": "[1.6]",
    "Icon": "PengBuildCard_230"
  },
  "5302": {
    "Id": 5302,
    "GroupId": 53,
    "Title": "PenguinCard.5302.1",
    "Desc": "PenguinCard.5302.2",
    "Rarity": 1,
    "Level": 2,
    "MaxLevel": 3,
    "SoldPrice": 10,
    "TriggerPhase": 3,
    "TriggerType": 3,
    "TriggerParam": "{\"3\":3}",
    "TriggerProbability": 100,
    "TriggerLimit": 1,
    "GrowthType": 1,
    "EffectType": 4,
    "EffectParam": "[3.2]",
    "Icon": "PengBuildCard_230"
  },
  "5303": {
    "Id": 5303,
    "GroupId": 53,
    "Title": "PenguinCard.5303.1",
    "Desc": "PenguinCard.5303.2",
    "Rarity": 1,
    "Level": 3,
    "MaxLevel": 3,
    "SoldPrice": 10,
    "TriggerPhase": 3,
    "TriggerType": 3,
    "TriggerParam": "{\"3\":3}",
    "TriggerProbability": 100,
    "TriggerLimit": 1,
    "GrowthType": 1,
    "EffectType": 4,
    "EffectParam": "[6.5]",
    "Icon": "PengBuildCard_230"
  },
  "6101": {
    "Id": 6101,
    "GroupId": 61,
    "Title": "PenguinCard.6101.1",
    "Desc": "PenguinCard.6101.2",
    "Rarity": 1,
    "Level": 1,
    "MaxLevel": 3,
    "SoldPrice": 10,
    "TriggerPhase": 3,
    "TriggerType": 3,
    "TriggerParam": "{\"1\":4}",
    "TriggerProbability": 100,
    "TriggerLimit": 1,
    "GrowthType": 1,
    "EffectType": 5,
    "EffectParam": "[2.5]",
    "Icon": "PengBuildCard_810"
  },
  "6102": {
    "Id": 6102,
    "GroupId": 61,
    "Title": "PenguinCard.6102.1",
    "Desc": "PenguinCard.6102.2",
    "Rarity": 1,
    "Level": 2,
    "MaxLevel": 3,
    "SoldPrice": 10,
    "TriggerPhase": 3,
    "TriggerType": 3,
    "TriggerParam": "{\"1\":4}",
    "TriggerProbability": 100,
    "TriggerLimit": 1,
    "GrowthType": 1,
    "EffectType": 5,
    "EffectParam": "[4]",
    "Icon": "PengBuildCard_810"
  },
  "6103": {
    "Id": 6103,
    "GroupId": 61,
    "Title": "PenguinCard.6103.1",
    "Desc": "PenguinCard.6103.2",
    "Rarity": 1,
    "Level": 3,
    "MaxLevel": 3,
    "SoldPrice": 10,
    "TriggerPhase": 3,
    "TriggerType": 3,
    "TriggerParam": "{\"1\":4}",
    "TriggerProbability": 100,
    "TriggerLimit": 1,
    "GrowthType": 1,
    "EffectType": 5,
    "EffectParam": "[6]",
    "Icon": "PengBuildCard_810"
  },
  "6201": {
    "Id": 6201,
    "GroupId": 62,
    "Title": "PenguinCard.6201.1",
    "Desc": "PenguinCard.6201.2",
    "Rarity": 1,
    "Level": 1,
    "MaxLevel": 3,
    "SoldPrice": 10,
    "TriggerPhase": 3,
    "TriggerType": 3,
    "TriggerParam": "{\"2\":4}",
    "TriggerProbability": 100,
    "TriggerLimit": 1,
    "GrowthType": 1,
    "EffectType": 5,
    "EffectParam": "[2.5]",
    "Icon": "PengBuildCard_820"
  },
  "6202": {
    "Id": 6202,
    "GroupId": 62,
    "Title": "PenguinCard.6202.1",
    "Desc": "PenguinCard.6202.2",
    "Rarity": 1,
    "Level": 2,
    "MaxLevel": 3,
    "SoldPrice": 10,
    "TriggerPhase": 3,
    "TriggerType": 3,
    "TriggerParam": "{\"2\":4}",
    "TriggerProbability": 100,
    "TriggerLimit": 1,
    "GrowthType": 1,
    "EffectType": 5,
    "EffectParam": "[4]",
    "Icon": "PengBuildCard_820"
  },
  "6203": {
    "Id": 6203,
    "GroupId": 62,
    "Title": "PenguinCard.6203.1",
    "Desc": "PenguinCard.6203.2",
    "Rarity": 1,
    "Level": 3,
    "MaxLevel": 3,
    "SoldPrice": 10,
    "TriggerPhase": 3,
    "TriggerType": 3,
    "TriggerParam": "{\"2\":4}",
    "TriggerProbability": 100,
    "TriggerLimit": 1,
    "GrowthType": 1,
    "EffectType": 5,
    "EffectParam": "[6]",
    "Icon": "PengBuildCard_820"
  },
  "6301": {
    "Id": 6301,
    "GroupId": 63,
    "Title": "PenguinCard.6301.1",
    "Desc": "PenguinCard.6301.2",
    "Rarity": 1,
    "Level": 1,
    "MaxLevel": 3,
    "SoldPrice": 10,
    "TriggerPhase": 3,
    "TriggerType": 3,
    "TriggerParam": "{\"3\":4}",
    "TriggerProbability": 100,
    "TriggerLimit": 1,
    "GrowthType": 1,
    "EffectType": 5,
    "EffectParam": "[2.5]",
    "Icon": "PengBuildCard_830"
  },
  "6302": {
    "Id": 6302,
    "GroupId": 63,
    "Title": "PenguinCard.6302.1",
    "Desc": "PenguinCard.6302.2",
    "Rarity": 1,
    "Level": 2,
    "MaxLevel": 3,
    "SoldPrice": 10,
    "TriggerPhase": 3,
    "TriggerType": 3,
    "TriggerParam": "{\"3\":4}",
    "TriggerProbability": 100,
    "TriggerLimit": 1,
    "GrowthType": 1,
    "EffectType": 5,
    "EffectParam": "[4]",
    "Icon": "PengBuildCard_830"
  },
  "6303": {
    "Id": 6303,
    "GroupId": 63,
    "Title": "PenguinCard.6303.1",
    "Desc": "PenguinCard.6303.2",
    "Rarity": 1,
    "Level": 3,
    "MaxLevel": 3,
    "SoldPrice": 10,
    "TriggerPhase": 3,
    "TriggerType": 3,
    "TriggerParam": "{\"3\":4}",
    "TriggerProbability": 100,
    "TriggerLimit": 1,
    "GrowthType": 1,
    "EffectType": 5,
    "EffectParam": "[6]",
    "Icon": "PengBuildCard_830"
  },
  "9101": {
    "Id": 9101,
    "GroupId": 91,
    "Title": "PenguinCard.9101.1",
    "Desc": "PenguinCard.9101.2",
    "Rarity": 1,
    "Level": 1,
    "MaxLevel": 5,
    "SoldPrice": 10,
    "TriggerPhase": 3,
    "TriggerType": 1,
    "TriggerProbability": 100,
    "TriggerLimit": 1,
    "GrowthType": 3,
    "GrowthTriggerPhase": 9,
    "GrowthTriggerType": 2,
    "GrowthTriggerParam": "[1]",
    "GrowthEffectParam": "[40]",
    "EffectType": 3,
    "EffectParam": "[0]",
    "Icon": "PengBuildCard_910"
  },
  "9102": {
    "Id": 9102,
    "GroupId": 91,
    "Title": "PenguinCard.9102.1",
    "Desc": "PenguinCard.9102.2",
    "Rarity": 1,
    "Level": 2,
    "MaxLevel": 5,
    "SoldPrice": 10,
    "TriggerPhase": 3,
    "TriggerType": 1,
    "TriggerProbability": 100,
    "TriggerLimit": 1,
    "GrowthType": 3,
    "GrowthTriggerPhase": 9,
    "GrowthTriggerType": 2,
    "GrowthTriggerParam": "[1]",
    "GrowthEffectParam": "[80]",
    "EffectType": 3,
    "EffectParam": "[0]",
    "Icon": "PengBuildCard_910"
  },
  "9103": {
    "Id": 9103,
    "GroupId": 91,
    "Title": "PenguinCard.9103.1",
    "Desc": "PenguinCard.9103.2",
    "Rarity": 1,
    "Level": 3,
    "MaxLevel": 5,
    "SoldPrice": 10,
    "TriggerPhase": 3,
    "TriggerType": 1,
    "TriggerProbability": 100,
    "TriggerLimit": 1,
    "GrowthType": 3,
    "GrowthTriggerPhase": 9,
    "GrowthTriggerType": 2,
    "GrowthTriggerParam": "[1]",
    "GrowthEffectParam": "[120]",
    "EffectType": 3,
    "EffectParam": "[0]",
    "Icon": "PengBuildCard_910"
  },
  "9104": {
    "Id": 9104,
    "GroupId": 91,
    "Title": "PenguinCard.9104.1",
    "Desc": "PenguinCard.9104.2",
    "Rarity": 1,
    "Level": 4,
    "MaxLevel": 5,
    "SoldPrice": 10,
    "TriggerPhase": 3,
    "TriggerType": 1,
    "TriggerProbability": 100,
    "TriggerLimit": 1,
    "GrowthType": 3,
    "GrowthTriggerPhase": 9,
    "GrowthTriggerType": 2,
    "GrowthTriggerParam": "[1]",
    "GrowthEffectParam": "[160]",
    "EffectType": 3,
    "EffectParam": "[0]",
    "Icon": "PengBuildCard_910"
  },
  "9105": {
    "Id": 9105,
    "GroupId": 91,
    "Title": "PenguinCard.9105.1",
    "Desc": "PenguinCard.9105.2",
    "Rarity": 1,
    "Level": 5,
    "MaxLevel": 5,
    "SoldPrice": 10,
    "TriggerPhase": 3,
    "TriggerType": 1,
    "TriggerProbability": 100,
    "TriggerLimit": 1,
    "GrowthType": 3,
    "GrowthTriggerPhase": 9,
    "GrowthTriggerType": 2,
    "GrowthTriggerParam": "[1]",
    "GrowthEffectParam": "[240]",
    "EffectType": 3,
    "EffectParam": "[0]",
    "Icon": "PengBuildCard_910"
  },
  "9201": {
    "Id": 9201,
    "GroupId": 92,
    "Title": "PenguinCard.9201.1",
    "Desc": "PenguinCard.9201.2",
    "Rarity": 1,
    "Level": 1,
    "MaxLevel": 5,
    "SoldPrice": 10,
    "TriggerPhase": 3,
    "TriggerType": 1,
    "TriggerProbability": 100,
    "TriggerLimit": 1,
    "GrowthType": 3,
    "GrowthTriggerPhase": 9,
    "GrowthTriggerType": 2,
    "GrowthTriggerParam": "[2]",
    "GrowthEffectParam": "[40]",
    "EffectType": 3,
    "EffectParam": "[0]",
    "Icon": "PengBuildCard_920"
  },
  "9202": {
    "Id": 9202,
    "GroupId": 92,
    "Title": "PenguinCard.9202.1",
    "Desc": "PenguinCard.9202.2",
    "Rarity": 1,
    "Level": 2,
    "MaxLevel": 5,
    "SoldPrice": 10,
    "TriggerPhase": 3,
    "TriggerType": 1,
    "TriggerProbability": 100,
    "TriggerLimit": 1,
    "GrowthType": 3,
    "GrowthTriggerPhase": 9,
    "GrowthTriggerType": 2,
    "GrowthTriggerParam": "[2]",
    "GrowthEffectParam": "[80]",
    "EffectType": 3,
    "EffectParam": "[0]",
    "Icon": "PengBuildCard_920"
  },
  "9203": {
    "Id": 9203,
    "GroupId": 92,
    "Title": "PenguinCard.9203.1",
    "Desc": "PenguinCard.9203.2",
    "Rarity": 1,
    "Level": 3,
    "MaxLevel": 5,
    "SoldPrice": 10,
    "TriggerPhase": 3,
    "TriggerType": 1,
    "TriggerProbability": 100,
    "TriggerLimit": 1,
    "GrowthType": 3,
    "GrowthTriggerPhase": 9,
    "GrowthTriggerType": 2,
    "GrowthTriggerParam": "[2]",
    "GrowthEffectParam": "[120]",
    "EffectType": 3,
    "EffectParam": "[0]",
    "Icon": "PengBuildCard_920"
  },
  "9204": {
    "Id": 9204,
    "GroupId": 92,
    "Title": "PenguinCard.9204.1",
    "Desc": "PenguinCard.9204.2",
    "Rarity": 1,
    "Level": 4,
    "MaxLevel": 5,
    "SoldPrice": 10,
    "TriggerPhase": 3,
    "TriggerType": 1,
    "TriggerProbability": 100,
    "TriggerLimit": 1,
    "GrowthType": 3,
    "GrowthTriggerPhase": 9,
    "GrowthTriggerType": 2,
    "GrowthTriggerParam": "[2]",
    "GrowthEffectParam": "[160]",
    "EffectType": 3,
    "EffectParam": "[0]",
    "Icon": "PengBuildCard_920"
  },
  "9205": {
    "Id": 9205,
    "GroupId": 92,
    "Title": "PenguinCard.9205.1",
    "Desc": "PenguinCard.9205.2",
    "Rarity": 1,
    "Level": 5,
    "MaxLevel": 5,
    "SoldPrice": 10,
    "TriggerPhase": 3,
    "TriggerType": 1,
    "TriggerProbability": 100,
    "TriggerLimit": 1,
    "GrowthType": 3,
    "GrowthTriggerPhase": 9,
    "GrowthTriggerType": 2,
    "GrowthTriggerParam": "[2]",
    "GrowthEffectParam": "[240]",
    "EffectType": 3,
    "EffectParam": "[0]",
    "Icon": "PengBuildCard_920"
  },
  "9301": {
    "Id": 9301,
    "GroupId": 93,
    "Title": "PenguinCard.9301.1",
    "Desc": "PenguinCard.9301.2",
    "Rarity": 1,
    "Level": 1,
    "MaxLevel": 5,
    "SoldPrice": 10,
    "TriggerPhase": 3,
    "TriggerType": 1,
    "TriggerProbability": 100,
    "TriggerLimit": 1,
    "GrowthType": 3,
    "GrowthTriggerPhase": 9,
    "GrowthTriggerType": 2,
    "GrowthTriggerParam": "[3]",
    "GrowthEffectParam": "[40]",
    "EffectType": 3,
    "EffectParam": "[0]",
    "Icon": "PengBuildCard_930"
  },
  "9302": {
    "Id": 9302,
    "GroupId": 93,
    "Title": "PenguinCard.9302.1",
    "Desc": "PenguinCard.9302.2",
    "Rarity": 1,
    "Level": 2,
    "MaxLevel": 5,
    "SoldPrice": 10,
    "TriggerPhase": 3,
    "TriggerType": 1,
    "TriggerProbability": 100,
    "TriggerLimit": 1,
    "GrowthType": 3,
    "GrowthTriggerPhase": 9,
    "GrowthTriggerType": 2,
    "GrowthTriggerParam": "[3]",
    "GrowthEffectParam": "[80]",
    "EffectType": 3,
    "EffectParam": "[0]",
    "Icon": "PengBuildCard_930"
  },
  "9303": {
    "Id": 9303,
    "GroupId": 93,
    "Title": "PenguinCard.9303.1",
    "Desc": "PenguinCard.9303.2",
    "Rarity": 1,
    "Level": 3,
    "MaxLevel": 5,
    "SoldPrice": 10,
    "TriggerPhase": 3,
    "TriggerType": 1,
    "TriggerProbability": 100,
    "TriggerLimit": 1,
    "GrowthType": 3,
    "GrowthTriggerPhase": 9,
    "GrowthTriggerType": 2,
    "GrowthTriggerParam": "[3]",
    "GrowthEffectParam": "[120]",
    "EffectType": 3,
    "EffectParam": "[0]",
    "Icon": "PengBuildCard_930"
  },
  "9304": {
    "Id": 9304,
    "GroupId": 93,
    "Title": "PenguinCard.9304.1",
    "Desc": "PenguinCard.9304.2",
    "Rarity": 1,
    "Level": 4,
    "MaxLevel": 5,
    "SoldPrice": 10,
    "TriggerPhase": 3,
    "TriggerType": 1,
    "TriggerProbability": 100,
    "TriggerLimit": 1,
    "GrowthType": 3,
    "GrowthTriggerPhase": 9,
    "GrowthTriggerType": 2,
    "GrowthTriggerParam": "[3]",
    "GrowthEffectParam": "[160]",
    "EffectType": 3,
    "EffectParam": "[0]",
    "Icon": "PengBuildCard_930"
  },
  "9305": {
    "Id": 9305,
    "GroupId": 93,
    "Title": "PenguinCard.9305.1",
    "Desc": "PenguinCard.9305.2",
    "Rarity": 1,
    "Level": 5,
    "MaxLevel": 5,
    "SoldPrice": 10,
    "TriggerPhase": 3,
    "TriggerType": 1,
    "TriggerProbability": 100,
    "TriggerLimit": 1,
    "GrowthType": 3,
    "GrowthTriggerPhase": 9,
    "GrowthTriggerType": 2,
    "GrowthTriggerParam": "[3]",
    "GrowthEffectParam": "[240]",
    "EffectType": 3,
    "EffectParam": "[0]",
    "Icon": "PengBuildCard_930"
  },
  "10101": {
    "Id": 10101,
    "GroupId": 101,
    "Title": "PenguinCard.10101.1",
    "Desc": "PenguinCard.10101.2",
    "Rarity": 1,
    "Level": 1,
    "MaxLevel": 5,
    "SoldPrice": 10,
    "TriggerPhase": 3,
    "TriggerType": 1,
    "TriggerProbability": 100,
    "TriggerLimit": 1,
    "GrowthType": 3,
    "GrowthTriggerPhase": 9,
    "GrowthTriggerType": 2,
    "GrowthTriggerParam": "[1]",
    "GrowthEffectParam": "[0.12]",
    "EffectType": 4,
    "EffectParam": "[0]",
    "Icon": "PengBuildCard_1010"
  },
  "10102": {
    "Id": 10102,
    "GroupId": 101,
    "Title": "PenguinCard.10102.1",
    "Desc": "PenguinCard.10102.2",
    "Rarity": 1,
    "Level": 2,
    "MaxLevel": 5,
    "SoldPrice": 10,
    "TriggerPhase": 3,
    "TriggerType": 1,
    "TriggerProbability": 100,
    "TriggerLimit": 1,
    "GrowthType": 3,
    "GrowthTriggerPhase": 9,
    "GrowthTriggerType": 2,
    "GrowthTriggerParam": "[1]",
    "GrowthEffectParam": "[0.16]",
    "EffectType": 4,
    "EffectParam": "[0]",
    "Icon": "PengBuildCard_1010"
  },
  "10103": {
    "Id": 10103,
    "GroupId": 101,
    "Title": "PenguinCard.10103.1",
    "Desc": "PenguinCard.10103.2",
    "Rarity": 1,
    "Level": 3,
    "MaxLevel": 5,
    "SoldPrice": 10,
    "TriggerPhase": 3,
    "TriggerType": 1,
    "TriggerProbability": 100,
    "TriggerLimit": 1,
    "GrowthType": 3,
    "GrowthTriggerPhase": 9,
    "GrowthTriggerType": 2,
    "GrowthTriggerParam": "[1]",
    "GrowthEffectParam": "[0.24]",
    "EffectType": 4,
    "EffectParam": "[0]",
    "Icon": "PengBuildCard_1010"
  },
  "10104": {
    "Id": 10104,
    "GroupId": 101,
    "Title": "PenguinCard.10104.1",
    "Desc": "PenguinCard.10104.2",
    "Rarity": 1,
    "Level": 4,
    "MaxLevel": 5,
    "SoldPrice": 10,
    "TriggerPhase": 3,
    "TriggerType": 1,
    "TriggerProbability": 100,
    "TriggerLimit": 1,
    "GrowthType": 3,
    "GrowthTriggerPhase": 9,
    "GrowthTriggerType": 2,
    "GrowthTriggerParam": "[1]",
    "GrowthEffectParam": "[0.32]",
    "EffectType": 4,
    "EffectParam": "[0]",
    "Icon": "PengBuildCard_1010"
  },
  "10105": {
    "Id": 10105,
    "GroupId": 101,
    "Title": "PenguinCard.10105.1",
    "Desc": "PenguinCard.10105.2",
    "Rarity": 1,
    "Level": 5,
    "MaxLevel": 5,
    "SoldPrice": 10,
    "TriggerPhase": 3,
    "TriggerType": 1,
    "TriggerProbability": 100,
    "TriggerLimit": 1,
    "GrowthType": 3,
    "GrowthTriggerPhase": 9,
    "GrowthTriggerType": 2,
    "GrowthTriggerParam": "[1]",
    "GrowthEffectParam": "[0.48]",
    "EffectType": 4,
    "EffectParam": "[0]",
    "Icon": "PengBuildCard_1010"
  },
  "10201": {
    "Id": 10201,
    "GroupId": 102,
    "Title": "PenguinCard.10201.1",
    "Desc": "PenguinCard.10201.2",
    "Rarity": 1,
    "Level": 1,
    "MaxLevel": 5,
    "SoldPrice": 10,
    "TriggerPhase": 3,
    "TriggerType": 1,
    "TriggerProbability": 100,
    "TriggerLimit": 1,
    "GrowthType": 3,
    "GrowthTriggerPhase": 9,
    "GrowthTriggerType": 2,
    "GrowthTriggerParam": "[2]",
    "GrowthEffectParam": "[0.12]",
    "EffectType": 4,
    "EffectParam": "[0]",
    "Icon": "PengBuildCard_1020"
  },
  "10202": {
    "Id": 10202,
    "GroupId": 102,
    "Title": "PenguinCard.10202.1",
    "Desc": "PenguinCard.10202.2",
    "Rarity": 1,
    "Level": 2,
    "MaxLevel": 5,
    "SoldPrice": 10,
    "TriggerPhase": 3,
    "TriggerType": 1,
    "TriggerProbability": 100,
    "TriggerLimit": 1,
    "GrowthType": 3,
    "GrowthTriggerPhase": 9,
    "GrowthTriggerType": 2,
    "GrowthTriggerParam": "[2]",
    "GrowthEffectParam": "[0.16]",
    "EffectType": 4,
    "EffectParam": "[0]",
    "Icon": "PengBuildCard_1020"
  },
  "10203": {
    "Id": 10203,
    "GroupId": 102,
    "Title": "PenguinCard.10203.1",
    "Desc": "PenguinCard.10203.2",
    "Rarity": 1,
    "Level": 3,
    "MaxLevel": 5,
    "SoldPrice": 10,
    "TriggerPhase": 3,
    "TriggerType": 1,
    "TriggerProbability": 100,
    "TriggerLimit": 1,
    "GrowthType": 3,
    "GrowthTriggerPhase": 9,
    "GrowthTriggerType": 2,
    "GrowthTriggerParam": "[2]",
    "GrowthEffectParam": "[0.24]",
    "EffectType": 4,
    "EffectParam": "[0]",
    "Icon": "PengBuildCard_1020"
  },
  "10204": {
    "Id": 10204,
    "GroupId": 102,
    "Title": "PenguinCard.10204.1",
    "Desc": "PenguinCard.10204.2",
    "Rarity": 1,
    "Level": 4,
    "MaxLevel": 5,
    "SoldPrice": 10,
    "TriggerPhase": 3,
    "TriggerType": 1,
    "TriggerProbability": 100,
    "TriggerLimit": 1,
    "GrowthType": 3,
    "GrowthTriggerPhase": 9,
    "GrowthTriggerType": 2,
    "GrowthTriggerParam": "[2]",
    "GrowthEffectParam": "[0.32]",
    "EffectType": 4,
    "EffectParam": "[0]",
    "Icon": "PengBuildCard_1020"
  },
  "10205": {
    "Id": 10205,
    "GroupId": 102,
    "Title": "PenguinCard.10205.1",
    "Desc": "PenguinCard.10205.2",
    "Rarity": 1,
    "Level": 5,
    "MaxLevel": 5,
    "SoldPrice": 10,
    "TriggerPhase": 3,
    "TriggerType": 1,
    "TriggerProbability": 100,
    "TriggerLimit": 1,
    "GrowthType": 3,
    "GrowthTriggerPhase": 9,
    "GrowthTriggerType": 2,
    "GrowthTriggerParam": "[2]",
    "GrowthEffectParam": "[0.48]",
    "EffectType": 4,
    "EffectParam": "[0]",
    "Icon": "PengBuildCard_1020"
  },
  "10301": {
    "Id": 10301,
    "GroupId": 103,
    "Title": "PenguinCard.10301.1",
    "Desc": "PenguinCard.10301.2",
    "Rarity": 1,
    "Level": 1,
    "MaxLevel": 5,
    "SoldPrice": 10,
    "TriggerPhase": 3,
    "TriggerType": 1,
    "TriggerProbability": 100,
    "TriggerLimit": 1,
    "GrowthType": 3,
    "GrowthTriggerPhase": 9,
    "GrowthTriggerType": 2,
    "GrowthTriggerParam": "[3]",
    "GrowthEffectParam": "[0.12]",
    "EffectType": 4,
    "EffectParam": "[0]",
    "Icon": "PengBuildCard_1030"
  },
  "10302": {
    "Id": 10302,
    "GroupId": 103,
    "Title": "PenguinCard.10302.1",
    "Desc": "PenguinCard.10302.2",
    "Rarity": 1,
    "Level": 2,
    "MaxLevel": 5,
    "SoldPrice": 10,
    "TriggerPhase": 3,
    "TriggerType": 1,
    "TriggerProbability": 100,
    "TriggerLimit": 1,
    "GrowthType": 3,
    "GrowthTriggerPhase": 9,
    "GrowthTriggerType": 2,
    "GrowthTriggerParam": "[3]",
    "GrowthEffectParam": "[0.16]",
    "EffectType": 4,
    "EffectParam": "[0]",
    "Icon": "PengBuildCard_1030"
  },
  "10303": {
    "Id": 10303,
    "GroupId": 103,
    "Title": "PenguinCard.10303.1",
    "Desc": "PenguinCard.10303.2",
    "Rarity": 1,
    "Level": 3,
    "MaxLevel": 5,
    "SoldPrice": 10,
    "TriggerPhase": 3,
    "TriggerType": 1,
    "TriggerProbability": 100,
    "TriggerLimit": 1,
    "GrowthType": 3,
    "GrowthTriggerPhase": 9,
    "GrowthTriggerType": 2,
    "GrowthTriggerParam": "[3]",
    "GrowthEffectParam": "[0.24]",
    "EffectType": 4,
    "EffectParam": "[0]",
    "Icon": "PengBuildCard_1030"
  },
  "10304": {
    "Id": 10304,
    "GroupId": 103,
    "Title": "PenguinCard.10304.1",
    "Desc": "PenguinCard.10304.2",
    "Rarity": 1,
    "Level": 4,
    "MaxLevel": 5,
    "SoldPrice": 10,
    "TriggerPhase": 3,
    "TriggerType": 1,
    "TriggerProbability": 100,
    "TriggerLimit": 1,
    "GrowthType": 3,
    "GrowthTriggerPhase": 9,
    "GrowthTriggerType": 2,
    "GrowthTriggerParam": "[3]",
    "GrowthEffectParam": "[0.32]",
    "EffectType": 4,
    "EffectParam": "[0]",
    "Icon": "PengBuildCard_1030"
  },
  "10305": {
    "Id": 10305,
    "GroupId": 103,
    "Title": "PenguinCard.10305.1",
    "Desc": "PenguinCard.10305.2",
    "Rarity": 1,
    "Level": 5,
    "MaxLevel": 5,
    "SoldPrice": 10,
    "TriggerPhase": 3,
    "TriggerType": 1,
    "TriggerProbability": 100,
    "TriggerLimit": 1,
    "GrowthType": 3,
    "GrowthTriggerPhase": 9,
    "GrowthTriggerType": 2,
    "GrowthTriggerParam": "[3]",
    "GrowthEffectParam": "[0.48]",
    "EffectType": 4,
    "EffectParam": "[0]",
    "Icon": "PengBuildCard_1030"
  },
  "11401": {
    "Id": 11401,
    "GroupId": 114,
    "Title": "PenguinCard.11401.1",
    "Desc": "PenguinCard.11401.2",
    "Rarity": 1,
    "Level": 1,
    "MaxLevel": 3,
    "SoldPrice": 10,
    "TriggerPhase": 3,
    "TriggerType": 1,
    "TriggerProbability": 100,
    "TriggerLimit": 1,
    "GrowthType": 2,
    "UpgradeResetGrowth": true,
    "GrowthTriggerPhase": 4,
    "GrowthTriggerType": 1,
    "GrowthEffectParam": "[-70]",
    "EffectType": 3,
    "EffectParam": "[160]",
    "Icon": "PengBuildCard_1140"
  },
  "11402": {
    "Id": 11402,
    "GroupId": 114,
    "Title": "PenguinCard.11402.1",
    "Desc": "PenguinCard.11402.2",
    "Rarity": 1,
    "Level": 2,
    "MaxLevel": 3,
    "SoldPrice": 10,
    "TriggerPhase": 3,
    "TriggerType": 1,
    "TriggerProbability": 100,
    "TriggerLimit": 1,
    "GrowthType": 2,
    "UpgradeResetGrowth": true,
    "GrowthTriggerPhase": 4,
    "GrowthTriggerType": 1,
    "GrowthEffectParam": "[-140]",
    "EffectType": 3,
    "EffectParam": "[320]",
    "Icon": "PengBuildCard_1140"
  },
  "11403": {
    "Id": 11403,
    "GroupId": 114,
    "Title": "PenguinCard.11403.1",
    "Desc": "PenguinCard.11403.2",
    "Rarity": 1,
    "Level": 3,
    "MaxLevel": 3,
    "SoldPrice": 10,
    "TriggerPhase": 3,
    "TriggerType": 1,
    "TriggerProbability": 100,
    "TriggerLimit": 1,
    "GrowthType": 2,
    "UpgradeResetGrowth": true,
    "GrowthTriggerPhase": 4,
    "GrowthTriggerType": 1,
    "GrowthEffectParam": "[-220]",
    "EffectType": 3,
    "EffectParam": "[480]",
    "Icon": "PengBuildCard_1140"
  },
  "12401": {
    "Id": 12401,
    "GroupId": 124,
    "Title": "PenguinCard.12401.1",
    "Desc": "PenguinCard.12401.2",
    "Rarity": 1,
    "Level": 1,
    "MaxLevel": 3,
    "SoldPrice": 10,
    "TriggerPhase": 3,
    "TriggerType": 1,
    "TriggerProbability": 100,
    "TriggerLimit": 1,
    "GrowthType": 2,
    "UpgradeResetGrowth": true,
    "GrowthTriggerPhase": 4,
    "GrowthTriggerType": 1,
    "GrowthEffectParam": "[-0.22]",
    "EffectType": 4,
    "EffectParam": "[0.48]",
    "Icon": "PengBuildCard_1240"
  },
  "12402": {
    "Id": 12402,
    "GroupId": 124,
    "Title": "PenguinCard.12402.1",
    "Desc": "PenguinCard.12402.2",
    "Rarity": 1,
    "Level": 2,
    "MaxLevel": 3,
    "SoldPrice": 10,
    "TriggerPhase": 3,
    "TriggerType": 1,
    "TriggerProbability": 100,
    "TriggerLimit": 1,
    "GrowthType": 2,
    "UpgradeResetGrowth": true,
    "GrowthTriggerPhase": 4,
    "GrowthTriggerType": 1,
    "GrowthEffectParam": "[-0.43]",
    "EffectType": 4,
    "EffectParam": "[0.96]",
    "Icon": "PengBuildCard_1240"
  },
  "12403": {
    "Id": 12403,
    "GroupId": 124,
    "Title": "PenguinCard.12403.1",
    "Desc": "PenguinCard.12403.2",
    "Rarity": 1,
    "Level": 3,
    "MaxLevel": 3,
    "SoldPrice": 10,
    "TriggerPhase": 3,
    "TriggerType": 1,
    "TriggerProbability": 100,
    "TriggerLimit": 1,
    "GrowthType": 2,
    "UpgradeResetGrowth": true,
    "GrowthTriggerPhase": 4,
    "GrowthTriggerType": 1,
    "GrowthEffectParam": "[-0.72]",
    "EffectType": 4,
    "EffectParam": "[1.6]",
    "Icon": "PengBuildCard_1240"
  },
  "13401": {
    "Id": 13401,
    "GroupId": 134,
    "Title": "PenguinCard.13401.1",
    "Desc": "PenguinCard.13401.2",
    "Rarity": 1,
    "Level": 1,
    "MaxLevel": 3,
    "SoldPrice": 10,
    "TriggerPhase": 6,
    "TriggerType": 1,
    "TriggerProbability": 100,
    "TriggerLimit": 3,
    "TriggerLimitParam": 1,
    "GrowthType": 1,
    "EffectType": 9,
    "EffectParam": "[20]",
    "Icon": "PengBuildCard_1340"
  },
  "13402": {
    "Id": 13402,
    "GroupId": 134,
    "Title": "PenguinCard.13402.1",
    "Desc": "PenguinCard.13402.2",
    "Rarity": 1,
    "Level": 2,
    "MaxLevel": 3,
    "SoldPrice": 10,
    "TriggerPhase": 6,
    "TriggerType": 1,
    "TriggerProbability": 100,
    "TriggerLimit": 3,
    "TriggerLimitParam": 1,
    "GrowthType": 1,
    "EffectType": 9,
    "EffectParam": "[30]",
    "Icon": "PengBuildCard_1340"
  },
  "13403": {
    "Id": 13403,
    "GroupId": 134,
    "Title": "PenguinCard.13403.1",
    "Desc": "PenguinCard.13403.2",
    "Rarity": 1,
    "Level": 3,
    "MaxLevel": 3,
    "SoldPrice": 10,
    "TriggerPhase": 6,
    "TriggerType": 1,
    "TriggerProbability": 100,
    "TriggerLimit": 3,
    "TriggerLimitParam": 1,
    "GrowthType": 1,
    "EffectType": 9,
    "EffectParam": "[40]",
    "Icon": "PengBuildCard_1340"
  },
  "14401": {
    "Id": 14401,
    "GroupId": 144,
    "Title": "PenguinCard.14401.1",
    "Desc": "PenguinCard.14401.2",
    "Rarity": 1,
    "Level": 1,
    "MaxLevel": 6,
    "SoldPrice": 10,
    "TriggerPhase": 3,
    "TriggerType": 1,
    "TriggerProbability": 100,
    "TriggerLimit": 1,
    "GrowthType": 2,
    "GrowthTriggerPhase": 8,
    "GrowthTriggerType": 3,
    "GrowthEffectParam": "[60]",
    "EffectType": 3,
    "EffectParam": "[0]",
    "Icon": "PengBuildCard_1440"
  },
  "14402": {
    "Id": 14402,
    "GroupId": 144,
    "Title": "PenguinCard.14402.1",
    "Desc": "PenguinCard.14402.2",
    "Rarity": 1,
    "Level": 2,
    "MaxLevel": 6,
    "SoldPrice": 10,
    "TriggerPhase": 3,
    "TriggerType": 1,
    "TriggerProbability": 100,
    "TriggerLimit": 1,
    "GrowthType": 2,
    "GrowthTriggerPhase": 8,
    "GrowthTriggerType": 3,
    "GrowthEffectParam": "[80]",
    "EffectType": 3,
    "EffectParam": "[0]",
    "Icon": "PengBuildCard_1440"
  },
  "14403": {
    "Id": 14403,
    "GroupId": 144,
    "Title": "PenguinCard.14403.1",
    "Desc": "PenguinCard.14403.2",
    "Rarity": 1,
    "Level": 3,
    "MaxLevel": 6,
    "SoldPrice": 10,
    "TriggerPhase": 3,
    "TriggerType": 1,
    "TriggerProbability": 100,
    "TriggerLimit": 1,
    "GrowthType": 2,
    "GrowthTriggerPhase": 8,
    "GrowthTriggerType": 3,
    "GrowthEffectParam": "[100]",
    "EffectType": 3,
    "EffectParam": "[0]",
    "Icon": "PengBuildCard_1440"
  },
  "14404": {
    "Id": 14404,
    "GroupId": 144,
    "Title": "PenguinCard.14404.1",
    "Desc": "PenguinCard.14404.2",
    "Rarity": 1,
    "Level": 4,
    "MaxLevel": 6,
    "SoldPrice": 10,
    "TriggerPhase": 3,
    "TriggerType": 1,
    "TriggerProbability": 100,
    "TriggerLimit": 1,
    "GrowthType": 2,
    "GrowthTriggerPhase": 8,
    "GrowthTriggerType": 3,
    "GrowthEffectParam": "[120]",
    "EffectType": 3,
    "EffectParam": "[0]",
    "Icon": "PengBuildCard_1440"
  },
  "14405": {
    "Id": 14405,
    "GroupId": 144,
    "Title": "PenguinCard.14405.1",
    "Desc": "PenguinCard.14405.2",
    "Rarity": 1,
    "Level": 5,
    "MaxLevel": 6,
    "SoldPrice": 10,
    "TriggerPhase": 3,
    "TriggerType": 1,
    "TriggerProbability": 100,
    "TriggerLimit": 1,
    "GrowthType": 2,
    "GrowthTriggerPhase": 8,
    "GrowthTriggerType": 3,
    "GrowthEffectParam": "[150]",
    "EffectType": 3,
    "EffectParam": "[0]",
    "Icon": "PengBuildCard_1440"
  },
  "14406": {
    "Id": 14406,
    "GroupId": 144,
    "Title": "PenguinCard.14406.1",
    "Desc": "PenguinCard.14406.2",
    "Rarity": 1,
    "Level": 6,
    "MaxLevel": 6,
    "SoldPrice": 10,
    "TriggerPhase": 3,
    "TriggerType": 1,
    "TriggerProbability": 100,
    "TriggerLimit": 1,
    "GrowthType": 2,
    "GrowthTriggerPhase": 8,
    "GrowthTriggerType": 3,
    "GrowthEffectParam": "[200]",
    "EffectType": 3,
    "EffectParam": "[0]",
    "Icon": "PengBuildCard_1440"
  },
  "15401": {
    "Id": 15401,
    "GroupId": 154,
    "Title": "PenguinCard.15401.1",
    "Desc": "PenguinCard.15401.2",
    "Rarity": 1,
    "Level": 1,
    "MaxLevel": 1,
    "SoldPrice": 10,
    "TriggerPhase": 3,
    "TriggerType": 1,
    "TriggerProbability": 100,
    "TriggerLimit": 1,
    "GrowthType": 2,
    "GrowthTriggerPhase": 3,
    "GrowthTriggerType": 4,
    "GrowthTriggerParam": "[7,5,4]",
    "GrowthEffectParam": "[0.5]",
    "EffectType": 4,
    "EffectParam": "[0.3]",
    "Icon": "PengBuildCard_1540"
  },
  "16401": {
    "Id": 16401,
    "GroupId": 164,
    "Title": "PenguinCard.16401.1",
    "Desc": "PenguinCard.16401.2",
    "Rarity": 1,
    "Level": 1,
    "MaxLevel": 1,
    "SoldPrice": 10,
    "TriggerPhase": 3,
    "TriggerType": 1,
    "TriggerProbability": 100,
    "TriggerLimit": 1,
    "GrowthType": 2,
    "GrowthTriggerPhase": 3,
    "GrowthTriggerType": 4,
    "GrowthTriggerParam": "[3,2,1]",
    "GrowthEffectParam": "[500]",
    "EffectType": 3,
    "EffectParam": "[300]",
    "Icon": "PengBuildCard_1640"
  },
  "17401": {
    "Id": 17401,
    "GroupId": 174,
    "Title": "PenguinCard.17401.1",
    "Desc": "PenguinCard.17401.2",
    "Rarity": 1,
    "Level": 1,
    "MaxLevel": 6,
    "SoldPrice": 10,
    "TriggerPhase": 3,
    "TriggerType": 6,
    "TriggerProbability": 100,
    "TriggerLimit": 1,
    "GrowthType": 1,
    "EffectType": 5,
    "EffectParam": "[1.3]",
    "Icon": "PengBuildCard_1740"
  },
  "17402": {
    "Id": 17402,
    "GroupId": 174,
    "Title": "PenguinCard.17402.1",
    "Desc": "PenguinCard.17402.2",
    "Rarity": 1,
    "Level": 2,
    "MaxLevel": 6,
    "SoldPrice": 10,
    "TriggerPhase": 3,
    "TriggerType": 6,
    "TriggerProbability": 100,
    "TriggerLimit": 1,
    "GrowthType": 1,
    "EffectType": 5,
    "EffectParam": "[1.5]",
    "Icon": "PengBuildCard_1740"
  },
  "17403": {
    "Id": 17403,
    "GroupId": 174,
    "Title": "PenguinCard.17403.1",
    "Desc": "PenguinCard.17403.2",
    "Rarity": 1,
    "Level": 3,
    "MaxLevel": 6,
    "SoldPrice": 10,
    "TriggerPhase": 3,
    "TriggerType": 6,
    "TriggerProbability": 100,
    "TriggerLimit": 1,
    "GrowthType": 1,
    "EffectType": 5,
    "EffectParam": "[1.7]",
    "Icon": "PengBuildCard_1740"
  },
  "17404": {
    "Id": 17404,
    "GroupId": 174,
    "Title": "PenguinCard.17404.1",
    "Desc": "PenguinCard.17404.2",
    "Rarity": 1,
    "Level": 4,
    "MaxLevel": 6,
    "SoldPrice": 10,
    "TriggerPhase": 3,
    "TriggerType": 6,
    "TriggerProbability": 100,
    "TriggerLimit": 1,
    "GrowthType": 1,
    "EffectType": 5,
    "EffectParam": "[2]",
    "Icon": "PengBuildCard_1740"
  },
  "17405": {
    "Id": 17405,
    "GroupId": 174,
    "Title": "PenguinCard.17405.1",
    "Desc": "PenguinCard.17405.2",
    "Rarity": 1,
    "Level": 5,
    "MaxLevel": 6,
    "SoldPrice": 10,
    "TriggerPhase": 3,
    "TriggerType": 6,
    "TriggerProbability": 100,
    "TriggerLimit": 1,
    "GrowthType": 1,
    "EffectType": 5,
    "EffectParam": "[2.5]",
    "Icon": "PengBuildCard_1740"
  },
  "17406": {
    "Id": 17406,
    "GroupId": 174,
    "Title": "PenguinCard.17406.1",
    "Desc": "PenguinCard.17406.2",
    "Rarity": 1,
    "Level": 6,
    "MaxLevel": 6,
    "SoldPrice": 10,
    "TriggerPhase": 3,
    "TriggerType": 6,
    "TriggerProbability": 100,
    "TriggerLimit": 1,
    "GrowthType": 1,
    "EffectType": 5,
    "EffectParam": "[3.3]",
    "Icon": "PengBuildCard_1740"
  },
  "18401": {
    "Id": 18401,
    "GroupId": 184,
    "Title": "PenguinCard.18401.1",
    "Desc": "PenguinCard.18401.2",
    "Rarity": 1,
    "Level": 1,
    "MaxLevel": 6,
    "SoldPrice": 10,
    "TriggerPhase": 3,
    "TriggerType": 7,
    "TriggerParam": "[5,4]",
    "TriggerProbability": 100,
    "TriggerLimit": 1,
    "GrowthType": 1,
    "EffectType": 5,
    "EffectParam": "[1.6]",
    "Icon": "PengBuildCard_1840"
  },
  "18402": {
    "Id": 18402,
    "GroupId": 184,
    "Title": "PenguinCard.18402.1",
    "Desc": "PenguinCard.18402.2",
    "Rarity": 1,
    "Level": 2,
    "MaxLevel": 6,
    "SoldPrice": 10,
    "TriggerPhase": 3,
    "TriggerType": 7,
    "TriggerParam": "[5,4]",
    "TriggerProbability": 100,
    "TriggerLimit": 1,
    "GrowthType": 1,
    "EffectType": 5,
    "EffectParam": "[1.9]",
    "Icon": "PengBuildCard_1840"
  },
  "18403": {
    "Id": 18403,
    "GroupId": 184,
    "Title": "PenguinCard.18403.1",
    "Desc": "PenguinCard.18403.2",
    "Rarity": 1,
    "Level": 3,
    "MaxLevel": 6,
    "SoldPrice": 10,
    "TriggerPhase": 3,
    "TriggerType": 7,
    "TriggerParam": "[5,4]",
    "TriggerProbability": 100,
    "TriggerLimit": 1,
    "GrowthType": 1,
    "EffectType": 5,
    "EffectParam": "[2.2]",
    "Icon": "PengBuildCard_1840"
  },
  "18404": {
    "Id": 18404,
    "GroupId": 184,
    "Title": "PenguinCard.18404.1",
    "Desc": "PenguinCard.18404.2",
    "Rarity": 1,
    "Level": 4,
    "MaxLevel": 6,
    "SoldPrice": 10,
    "TriggerPhase": 3,
    "TriggerType": 7,
    "TriggerParam": "[5,4]",
    "TriggerProbability": 100,
    "TriggerLimit": 1,
    "GrowthType": 1,
    "EffectType": 5,
    "EffectParam": "[2.5]",
    "Icon": "PengBuildCard_1840"
  },
  "18405": {
    "Id": 18405,
    "GroupId": 184,
    "Title": "PenguinCard.18405.1",
    "Desc": "PenguinCard.18405.2",
    "Rarity": 1,
    "Level": 5,
    "MaxLevel": 6,
    "SoldPrice": 10,
    "TriggerPhase": 3,
    "TriggerType": 7,
    "TriggerParam": "[5,4]",
    "TriggerProbability": 100,
    "TriggerLimit": 1,
    "GrowthType": 1,
    "EffectType": 5,
    "EffectParam": "[3]",
    "Icon": "PengBuildCard_1840"
  },
  "18406": {
    "Id": 18406,
    "GroupId": 184,
    "Title": "PenguinCard.18406.1",
    "Desc": "PenguinCard.18406.2",
    "Rarity": 1,
    "Level": 6,
    "MaxLevel": 6,
    "SoldPrice": 10,
    "TriggerPhase": 3,
    "TriggerType": 7,
    "TriggerParam": "[5,4]",
    "TriggerProbability": 100,
    "TriggerLimit": 1,
    "GrowthType": 1,
    "EffectType": 5,
    "EffectParam": "[4]",
    "Icon": "PengBuildCard_1840"
  },
  "19401": {
    "Id": 19401,
    "GroupId": 194,
    "Title": "PenguinCard.19401.1",
    "Desc": "PenguinCard.19401.2",
    "Rarity": 1,
    "Level": 1,
    "MaxLevel": 6,
    "SoldPrice": 10,
    "TriggerPhase": 3,
    "TriggerType": 3,
    "TriggerParam": "{\"1\":1,\"2\":1,\"3\":1}",
    "TriggerProbability": 100,
    "TriggerLimit": 1,
    "GrowthType": 1,
    "EffectType": 4,
    "EffectParam": "[0.6]",
    "Icon": "PengBuildCard_1940"
  },
  "19402": {
    "Id": 19402,
    "GroupId": 194,
    "Title": "PenguinCard.19402.1",
    "Desc": "PenguinCard.19402.2",
    "Rarity": 1,
    "Level": 2,
    "MaxLevel": 6,
    "SoldPrice": 10,
    "TriggerPhase": 3,
    "TriggerType": 3,
    "TriggerParam": "{\"1\":1,\"2\":1,\"3\":1}",
    "TriggerProbability": 100,
    "TriggerLimit": 1,
    "GrowthType": 1,
    "EffectType": 4,
    "EffectParam": "[0.8]",
    "Icon": "PengBuildCard_1940"
  },
  "19403": {
    "Id": 19403,
    "GroupId": 194,
    "Title": "PenguinCard.19403.1",
    "Desc": "PenguinCard.19403.2",
    "Rarity": 1,
    "Level": 3,
    "MaxLevel": 6,
    "SoldPrice": 10,
    "TriggerPhase": 3,
    "TriggerType": 3,
    "TriggerParam": "{\"1\":1,\"2\":1,\"3\":1}",
    "TriggerProbability": 100,
    "TriggerLimit": 1,
    "GrowthType": 1,
    "EffectType": 4,
    "EffectParam": "[1]",
    "Icon": "PengBuildCard_1940"
  },
  "19404": {
    "Id": 19404,
    "GroupId": 194,
    "Title": "PenguinCard.19404.1",
    "Desc": "PenguinCard.19404.2",
    "Rarity": 1,
    "Level": 4,
    "MaxLevel": 6,
    "SoldPrice": 10,
    "TriggerPhase": 3,
    "TriggerType": 3,
    "TriggerParam": "{\"1\":1,\"2\":1,\"3\":1}",
    "TriggerProbability": 100,
    "TriggerLimit": 1,
    "GrowthType": 1,
    "EffectType": 4,
    "EffectParam": "[1.3]",
    "Icon": "PengBuildCard_1940"
  },
  "19405": {
    "Id": 19405,
    "GroupId": 194,
    "Title": "PenguinCard.19405.1",
    "Desc": "PenguinCard.19405.2",
    "Rarity": 1,
    "Level": 5,
    "MaxLevel": 6,
    "SoldPrice": 10,
    "TriggerPhase": 3,
    "TriggerType": 3,
    "TriggerParam": "{\"1\":1,\"2\":1,\"3\":1}",
    "TriggerProbability": 100,
    "TriggerLimit": 1,
    "GrowthType": 1,
    "EffectType": 4,
    "EffectParam": "[1.6]",
    "Icon": "PengBuildCard_1940"
  },
  "19406": {
    "Id": 19406,
    "GroupId": 194,
    "Title": "PenguinCard.19406.1",
    "Desc": "PenguinCard.19406.2",
    "Rarity": 1,
    "Level": 6,
    "MaxLevel": 6,
    "SoldPrice": 10,
    "TriggerPhase": 3,
    "TriggerType": 3,
    "TriggerParam": "{\"1\":1,\"2\":1,\"3\":1}",
    "TriggerProbability": 100,
    "TriggerLimit": 1,
    "GrowthType": 1,
    "EffectType": 4,
    "EffectParam": "[2]",
    "Icon": "PengBuildCard_1940"
  }
}